pythonai/__init__.py
pythonai/core.py
InnoWaveAI-0.1.6.dist-info/METADATA
InnoWaveAI-0.1.6.dist-info/WHEEL
InnoWaveAI-0.1.6.dist-info/top_level.txt
InnoWaveAI-0.1.6.dist-info/RECORD
