Metadata-Version: 2.1
Name: InnoWaveAI
Version: 0.1.6
Summary: Библиотека для генерации кода с использованием Together AI
Home-page: UNKNOWN
Author: InnoWave
Author-email: bodnar.2009@inbox.ru
License: UNKNOWN
Platform: UNKNOWN
Classifier: Programming Language :: Python :: 3
Classifier: License :: OSI Approved :: MIT License
Classifier: Operating System :: OS Independent
Requires-Python: >=3.6
